topsis_saksham_102303157/__init__.py
topsis_saksham_102303157/topsis.py
topsis_saksham_102303157-1.0.0.dist-info/licenses/LICENSE
topsis_saksham_102303157-1.0.0.dist-info/METADATA
topsis_saksham_102303157-1.0.0.dist-info/WHEEL
topsis_saksham_102303157-1.0.0.dist-info/entry_points.txt
topsis_saksham_102303157-1.0.0.dist-info/top_level.txt
topsis_saksham_102303157-1.0.0.dist-info/RECORD
